vibesum/__init__.py
vibesum/ai.py
vibesum/py.typed
vibesum-0.1.1.dist-info/METADATA
vibesum-0.1.1.dist-info/WHEEL
vibesum-0.1.1.dist-info/licenses/LICENSE
vibesum-0.1.1.dist-info/RECORD
