Metadata-Version: 2.4
Name: vibesum
Version: 0.1.1
Summary: Addition library that uses GPT to add two numbers
Author-email: Taha Parker <tahayparker@gmail.com>
License-File: LICENSE
Requires-Python: >=3.10
Requires-Dist: openai>=1.95.1
Requires-Dist: pydantic>=2.11.7
Requires-Dist: typing-extensions>=4.14.1
